adafruit_bh1750.py
adafruit_circuitpython_bh1750-1.1.17.dist-info/licenses/LICENSE
adafruit_circuitpython_bh1750-1.1.17.dist-info/METADATA
adafruit_circuitpython_bh1750-1.1.17.dist-info/WHEEL
adafruit_circuitpython_bh1750-1.1.17.dist-info/top_level.txt
adafruit_circuitpython_bh1750-1.1.17.dist-info/RECORD
